{
    "title": "CR-SO, OT-GW, OT-SO",
    "description": "Crossing stand-on, overtaking give-way situation and overtaking stand-on situations with three target ships.",
    "ownShip": {
        "static": {
            "id": "da41746c-26eb-449d-b89d-c11633d33163",
            "length": 122.0,
            "width": 20.0,
            "height": 8.0,
            "speedMax": 17.0,
            "mmsi": 257847600,
            "name": "BASTO VI",
            "shipType": "Passenger"
        },
        "initial": {
            "position": {
                "latitude": 58.763449,
                "longitude": 10.490654
            },
            "sog": 10.0,
            "cog": 0.0,
            "heading": 0.0,
            "navStatus": "Under way using engine"
        },
        "waypoints": [
            {
                "position": {
                    "latitude": 58.763449,
                    "longitude": 10.490654
                }
            },
            {
                "position": {
                    "latitude": 58.92969579,
                    "longitude": 10.490654
                }
            }
        ]
    },
    "targetShips": [
        {
            "static": {
                "id": "32f5ddb7-a825-4fe7-8c83-b20991b093a4",
                "length": 50.0,
                "width": 10.0,
                "height": 8.0,
                "speedMax": 15.0,
                "name": "CANOLE",
                "shipType": "Cargo"
            },
            "initial": {
                "position": {
                    "latitude": 58.79309232,
                    "longitude": 10.36827418
                },
                "sog": 14.0,
                "cog": 74.66,
                "heading": 74.66,
                "navStatus": "Under way using engine"
            },
            "waypoints": [
                {
                    "position": {
                        "latitude": 58.79309232,
                        "longitude": 10.36827418
                    }
                },
                {
                    "position": {
                        "latitude": 58.85466472,
                        "longitude": 10.80021717
                    }
                }
            ]
        },
        {
            "static": {
                "id": "3c2edcef-a2aa-44a8-9d98-cac29d7529a4",
                "length": 178.0,
                "width": 30.0,
                "height": 30.0,
                "speedMax": 21.0,
                "name": "BASTO VI",
                "shipType": "Passenger"
            },
            "initial": {
                "position": {
                    "latitude": 58.8069534,
                    "longitude": 10.51310124
                },
                "sog": 4.1,
                "cog": 335.64,
                "heading": 335.64,
                "navStatus": "Under way using engine"
            },
            "waypoints": [
                {
                    "position": {
                        "latitude": 58.8069534,
                        "longitude": 10.51310124
                    }
                },
                {
                    "position": {
                        "latitude": 58.86877953,
                        "longitude": 10.45921366
                    }
                }
            ]
        },
        {
            "static": {
                "id": "7283426d-90ba-4111-90c2-c79c7e22a63c",
                "length": 50.0,
                "width": 10.0,
                "height": 8.0,
                "speedMax": 15.0,
                "name": "CANOLE",
                "shipType": "Cargo"
            },
            "initial": {
                "position": {
                    "latitude": 58.73057382,
                    "longitude": 10.49618373
                },
                "sog": 15.9,
                "cog": 358.16,
                "heading": 358.16,
                "navStatus": "Under way using engine"
            },
            "waypoints": [
                {
                    "position": {
                        "latitude": 58.73057382,
                        "longitude": 10.49618373
                    }
                },
                {
                    "position": {
                        "latitude": 58.99544895,
                        "longitude": 10.47976827
                    }
                }
            ]
        }
    ]
}